stigg_sdk/__init__.py
stigg_sdk/sdk.py
stigg_sdk-0.687.3.dist-info/LICENSE
stigg_sdk-0.687.3.dist-info/METADATA
stigg_sdk-0.687.3.dist-info/WHEEL
stigg_sdk-0.687.3.dist-info/RECORD
