Metadata-Version: 2.1
Name: stigg-sdk
Version: 0.687.3
Summary: 
Author: Stigg
Author-email: support@stigg.io
Requires-Python: >=3.9,<4.0
Classifier: Programming Language :: Python :: 3
Classifier: Programming Language :: Python :: 3.9
Classifier: Programming Language :: Python :: 3.10
Classifier: Programming Language :: Python :: 3.11
Requires-Dist: betterproto[compiler] (>=2.0.0b6,<3.0.0)
Requires-Dist: grpcio-tools (>=1.59.0,<2.0.0)
Requires-Dist: httpx (==0.24.1)
Requires-Dist: pydantic (==1.10.8)
Requires-Dist: stigg-api-client-v2 (>=0.677.0,<0.678.0)
Requires-Dist: tenacity (>=8.2.2,<9.0.0)
